pytest_expected/plugin.py
pytest_expected-0.1.1.dist-info/METADATA
pytest_expected-0.1.1.dist-info/WHEEL
pytest_expected-0.1.1.dist-info/entry_points.txt
pytest_expected-0.1.1.dist-info/top_level.txt
pytest_expected-0.1.1.dist-info/RECORD
